{
	"info": {
		"_postman_id": "8d1521f4-9de3-4c5c-9029-d44e57321488",
		"name": "TaskManager",
		"schema": "https://schema.getpostman.com/json/collection/v2.1.0/collection.json",
		"_exporter_id": "39820565"
	},
	"item": [
		{
			"name": "Get All Tasks",
			"request": {
				"method": "GET",
				"header": [],
				"url": {
					"raw": "{{URL}}/tasks",
					"host": [
						"{{URL}}"
					],
					"path": [
						"tasks"
					]
				}
			},
			"response": []
		},
		{
			"name": "Create Task",
			"request": {
				"method": "POST",
				"header": [],
				"body": {
					"mode": "raw",
					"raw": "{\r\n    \"name\":\"Tesing task\"\r\n    \r\n}",
					"options": {
						"raw": {
							"language": "json"
						}
					}
				},
				"url": {
					"raw": "{{URL}}/tasks",
					"host": [
						"{{URL}}"
					],
					"path": [
						"tasks"
					]
				}
			},
			"response": []
		},
		{
			"name": "Get Single Task",
			"protocolProfileBehavior": {
				"disableBodyPruning": true
			},
			"request": {
				"method": "GET",
				"header": [],
				"body": {
					"mode": "raw",
					"raw": "",
					"options": {
						"raw": {
							"language": "json"
						}
					}
				},
				"url": {
					"raw": "{{URL}}/tasks/674b0d1ee3bc2261309ceeca",
					"host": [
						"{{URL}}"
					],
					"path": [
						"tasks",
						"674b0d1ee3bc2261309ceeca"
					]
				}
			},
			"response": []
		},
		{
			"name": "Update Task",
			"request": {
				"method": "PATCH",
				"header": [],
				"body": {
					"mode": "raw",
					"raw": "{\r\n    \"name\":\"abc\",\r\n    \"completed\":true\r\n}",
					"options": {
						"raw": {
							"language": "json"
						}
					}
				},
				"url": {
					"raw": "{{URL}}/tasks/674b0e5f456014c01c26e875",
					"host": [
						"{{URL}}"
					],
					"path": [
						"tasks",
						"674b0e5f456014c01c26e875"
					]
				}
			},
			"response": []
		},
		{
			"name": "Detele Task",
			"request": {
				"method": "DELETE",
				"header": [],
				"body": {
					"mode": "raw",
					"raw": "",
					"options": {
						"raw": {
							"language": "json"
						}
					}
				},
				"url": {
					"raw": "{{URL}}/tasks/674b0c8de3bc2261309ceec9",
					"host": [
						"{{URL}}"
					],
					"path": [
						"tasks",
						"674b0c8de3bc2261309ceec9"
					]
				}
			},
			"response": []
		}
	]
}